[{"id":"87ZdCB","name":"Main Brewery","streetAddress":"Römermauer 3","locality":"Bitburg","region":"Rheinland-Pfalz","postalCode":"D-54634","latitude":49.972255,"longitude":6.52291,"isPrimary":"N","inPlanning":"N","isClosed":"N","openToPublic":"Y","locationType":"micro","locationTypeDisplay":"Micro Brewery","countryIsoCode":"DE","status":"verified","statusDisplay":"Verified","createDate":"2012-08-12 14:47:10","updateDate":"2014-07-23 19:11:34","country":{"isoCode":"DE","name":"GERMANY","displayName":"Germany","isoThree":"DEU","numberCode":276,"createDate":"2012-01-03 02:41:33"}},{"id":"5nFb8E","name":"Main Brewery","streetAddress":"Silberstraße 28","locality":"Scheibenberg-Oberscheibe","region":"Saxony","postalCode":"09481","isPrimary":"Y","inPlanning":"N","isClosed":"N","openToPublic":"Y","locationType":"micro","locationTypeDisplay":"Micro Brewery","countryIsoCode":"DE","status":"verified","statusDisplay":"Verified","createDate":"2012-08-12 23:54:31","updateDate":"2014-07-23 19:11:34","country":{"isoCode":"DE","name":"GERMANY","displayName":"Germany","isoThree":"DEU","numberCode":276,"createDate":"2012-01-03 02:41:33"}}]